sqlitemulti/__init__.py
sqlitemulti/sqlitemulti.py
sqlitemulti-0.0.2.dist-info/AUTHORS.rst
sqlitemulti-0.0.2.dist-info/LICENSE
sqlitemulti-0.0.2.dist-info/METADATA
sqlitemulti-0.0.2.dist-info/WHEEL
sqlitemulti-0.0.2.dist-info/top_level.txt
sqlitemulti-0.0.2.dist-info/RECORD
