Metadata-Version: 2.1
Name: sqlitemulti
Version: 0.0.2
Summary: A Sqlite wrapper to use a sqlite DB from several threads, optionaly in a dedicated process of its own.
Home-page: https://github.com/EggPool/sqlitemulti
Author: EggdraSyl
Author-email: dev@eggpool.net
License: MIT license
Keywords: sqlitemulti
Platform: UNKNOWN
Classifier: Development Status :: 2 - Pre-Alpha
Classifier: Intended Audience :: Developers
Classifier: License :: OSI Approved :: MIT License
Classifier: Natural Language :: English
Classifier: Programming Language :: Python :: 2
Classifier: Programming Language :: Python :: 2.7
Classifier: Programming Language :: Python :: 3
Classifier: Programming Language :: Python :: 3.4
Classifier: Programming Language :: Python :: 3.5
Classifier: Programming Language :: Python :: 3.6
Classifier: Programming Language :: Python :: 3.7
